z3c.baseregistry-3.0-py3.9-nspkg.pth
z3c/baseregistry/README.rst
z3c/baseregistry/__init__.py
z3c/baseregistry/baseregistry.py
z3c/baseregistry/meta.zcml
z3c/baseregistry/zcml.py
z3c/baseregistry/browser/README.rst
z3c/baseregistry/browser/__init__.py
z3c/baseregistry/browser/base.py
z3c/baseregistry/browser/configure.zcml
z3c/baseregistry/browser/ftesting.zcml
z3c/baseregistry/browser/tests.py
z3c/baseregistry/tests/__init__.py
z3c/baseregistry/tests/base-overrides.zcml
z3c/baseregistry/tests/custom-overrides.zcml
z3c/baseregistry/tests/test_zcml.py
z3c/baseregistry/tests/testdoc.py
z3c.baseregistry-3.0.dist-info/LICENSE.txt
z3c.baseregistry-3.0.dist-info/METADATA
z3c.baseregistry-3.0.dist-info/WHEEL
z3c.baseregistry-3.0.dist-info/namespace_packages.txt
z3c.baseregistry-3.0.dist-info/top_level.txt
z3c.baseregistry-3.0.dist-info/RECORD
