Metadata-Version: 2.1
Name: z3c.baseregistry
Version: 3.0
Summary: Manage IComponents instances using Python code and ZCML.
Home-page: https://github.com/zopefoundation/z3c.baseregistry
Author: Stephan Richter, Roger Ineichen and the Zope Community
Author-email: zope-dev@zope.dev
License: ZPL 2.1
Keywords: zope3 z3c component global registry baseregistry
Classifier: Development Status :: 5 - Production/Stable
Classifier: Environment :: Web Environment
Classifier: Intended Audience :: Developers
Classifier: License :: OSI Approved :: Zope Public License
Classifier: Programming Language :: Python
Classifier: Programming Language :: Python :: 3
Classifier: Programming Language :: Python :: 3.7
Classifier: Programming Language :: Python :: 3.8
Classifier: Programming Language :: Python :: 3.9
Classifier: Programming Language :: Python :: 3.10
Classifier: Programming Language :: Python :: 3.11
Classifier: Programming Language :: Python :: Implementation :: CPython
Classifier: Programming Language :: Python :: Implementation :: PyPy
Classifier: Natural Language :: English
Classifier: Operating System :: OS Independent
Classifier: Topic :: Internet :: WWW/HTTP
Classifier: Framework :: Zope :: 3
Requires-Python: >=3.7
License-File: LICENSE.txt
Requires-Dist: setuptools
Requires-Dist: zope.component[hook,zcml] (>=4.5.0)
Requires-Dist: zope.configuration (>=4.3.0)
Requires-Dist: zope.i18nmessageid (>=2.2)
Requires-Dist: zope.interface
Requires-Dist: zope.schema (>=4.9.0)
Requires-Dist: zope.site
Provides-Extra: test
Requires-Dist: zope.app.appsetup ; extra == 'test'
Requires-Dist: zope.app.authentication ; extra == 'test'
Requires-Dist: zope.app.basicskin (>=4.0.0) ; extra == 'test'
Requires-Dist: zope.app.container (>=4.0.0) ; extra == 'test'
Requires-Dist: zope.app.form (>=5.0.0) ; extra == 'test'
Requires-Dist: zope.app.publisher ; extra == 'test'
Requires-Dist: zope.app.publication ; extra == 'test'
Requires-Dist: zope.app.rotterdam (>=4.0.0) ; extra == 'test'
Requires-Dist: zope.app.schema (>=4.0.0) ; extra == 'test'
Requires-Dist: zope.app.wsgi ; extra == 'test'
Requires-Dist: zope.browserpage ; extra == 'test'
Requires-Dist: zope.browserresource ; extra == 'test'
Requires-Dist: zope.container ; extra == 'test'
Requires-Dist: zope.formlib ; extra == 'test'
Requires-Dist: zope.login ; extra == 'test'
Requires-Dist: zope.principalannotation ; extra == 'test'
Requires-Dist: zope.principalregistry ; extra == 'test'
Requires-Dist: zope.publisher ; extra == 'test'
Requires-Dist: zope.securitypolicy ; extra == 'test'
Requires-Dist: zope.testbrowser (>=5.2) ; extra == 'test'
Requires-Dist: zope.testing ; extra == 'test'
Requires-Dist: zope.testrunner ; extra == 'test'
Requires-Dist: zope.traversing (>=4.1.0) ; extra == 'test'
Requires-Dist: webtest ; extra == 'test'
Provides-Extra: zmi
Requires-Dist: zope.formlib ; extra == 'zmi'
